{
  "updated_at": "2026-07-18T09:01:02.541911+09:00",
  "updated_at_display": "2026-07-18 09:01:02 KST",
  "script_version": "v9.0 - 2026-07-14 (자동 토큰갱신저장 + 실패알림)",
  "weather": {
    "location": "서울",
    "current": {
      "icon": "🌦️",
      "label": "약한 이슬비",
      "temp": 24.7,
      "humidity": 92,
      "wind": 6.5
    },
    "daily": [
      {
        "date": "07/18",
        "weekday": "토",
        "icon": "🌧️",
        "label": "강한 비",
        "max": 27.0,
        "min": 22.0,
        "rain": 100
      },
      {
        "date": "07/19",
        "weekday": "일",
        "icon": "🌦️",
        "label": "강한 이슬비",
        "max": 27.0,
        "min": 23.0,
        "rain": 73
      },
      {
        "date": "07/20",
        "weekday": "월",
        "icon": "☁️",
        "label": "흐림",
        "max": 28.0,
        "min": 23.0,
        "rain": 82
      },
      {
        "date": "07/21",
        "weekday": "화",
        "icon": "⛈️",
        "label": "천둥번개",
        "max": 28.0,
        "min": 23.0,
        "rain": 96
      }
    ]
  },
  "weather_seoul": {
    "location": "서울",
    "current": {
      "icon": "🌦️",
      "label": "약한 이슬비",
      "temp": 24.7,
      "humidity": 92,
      "wind": 6.5
    },
    "daily": [
      {
        "date": "07/18",
        "weekday": "토",
        "icon": "🌧️",
        "label": "강한 비",
        "max": 27.0,
        "min": 22.0,
        "rain": 100
      },
      {
        "date": "07/19",
        "weekday": "일",
        "icon": "🌦️",
        "label": "강한 이슬비",
        "max": 27.0,
        "min": 23.0,
        "rain": 73
      },
      {
        "date": "07/20",
        "weekday": "월",
        "icon": "☁️",
        "label": "흐림",
        "max": 28.0,
        "min": 23.0,
        "rain": 82
      },
      {
        "date": "07/21",
        "weekday": "화",
        "icon": "⛈️",
        "label": "천둥번개",
        "max": 28.0,
        "min": 23.0,
        "rain": 96
      }
    ]
  },
  "weather_bundang": {
    "location": "분당",
    "current": {
      "icon": "🌦️",
      "label": "이슬비",
      "temp": 24.9,
      "humidity": 99,
      "wind": 20.8
    },
    "daily": [
      {
        "date": "07/18",
        "weekday": "토",
        "icon": "🌧️",
        "label": "강한 비",
        "max": 27.0,
        "min": 22.0,
        "rain": 100
      },
      {
        "date": "07/19",
        "weekday": "일",
        "icon": "🌧️",
        "label": "강한 비",
        "max": 27.0,
        "min": 23.0,
        "rain": 82
      },
      {
        "date": "07/20",
        "weekday": "월",
        "icon": "☁️",
        "label": "흐림",
        "max": 27.0,
        "min": 22.0,
        "rain": 83
      },
      {
        "date": "07/21",
        "weekday": "화",
        "icon": "⛈️",
        "label": "천둥번개",
        "max": 28.0,
        "min": 22.0,
        "rain": 100
      }
    ]
  },
  "indices": [
    {
      "name": "코스피",
      "value": "6,820.60",
      "change": "▼6.37%"
    },
    {
      "name": "코스닥",
      "value": "791.84",
      "change": "▼4.53%"
    }
  ],
  "global_indices": [
    {
      "name": "다우존스",
      "value": "52,146.42",
      "change": "▼0.77%"
    },
    {
      "name": "나스닥",
      "value": "25,520.24",
      "change": "▼1.40%"
    },
    {
      "name": "S&P 500",
      "value": "7,457.69",
      "change": "▼1.01%"
    }
  ],
  "movers": {
    "up": [
      {
        "code": "044380",
        "name": "주연테크",
        "change": "▲30.00%"
      },
      {
        "code": "011090",
        "name": "에넥스",
        "change": "▲29.95%"
      },
      {
        "code": "002070",
        "name": "비비안",
        "change": "▲29.94%"
      }
    ],
    "down": [
      {
        "code": "006490",
        "name": "프리티",
        "change": "▲24.06%"
      },
      {
        "code": "520101",
        "name": "미래에셋 레버리지 SK하이닉스 단일종목ETN",
        "change": "▲23.16%"
      },
      {
        "code": "760013",
        "name": "키움 레버리지 반도체TOP10 ETN",
        "change": "▲20.65%"
      }
    ],
    "volume": [
      {
        "code": "252670",
        "name": "KODEX 200선물인버스2X",
        "change": "▲13.64%"
      },
      {
        "code": "114800",
        "name": "KODEX 인버스",
        "change": "▲6.85%"
      },
      {
        "code": "252710",
        "name": "TIGER 200선물인버스2X",
        "change": "▲15.05%"
      }
    ]
  },
  "headlines": {
    "정치": [
      "북한 군대가 ‘뇌물 공화국’이 된 까닭은…부패 대명사된 박희철 전 총정치국 ...",
      "미군 정찰기 한반도 상공 비행 부쩍 증가",
      "제헌절에 개헌론 재점화… 조정식 “22대 국회내 매듭”",
      "국회의장 “내년 개헌안 마련하자” 국힘 “원 구성 마무리부터”"
    ],
    "경제": [
      "주담대 반토막에 카드론 한도 축소… 신혼부부들 ‘돈줄 막힐까’ 전전긍긍",
      "기후동행카드 종료 코앞…“난 이제 할인 못 받아?” 이용자 불만↑",
      "김시우, 시즌 마지막 메이저 디오픈 2R 공동 5위…임성재 공동 25위",
      "車 만들고 수출하던 대기업 영업맨, 바이올린을 깎다[은퇴 레시피]"
    ],
    "사회": [
      "“범죄피해 당하고 나서야 경찰 수사 잘못될 수 있다는 걸 알게 됐어요”",
      "부부싸움 중 집에 불 지른 60대 현행범 체포",
      "수도권 140㎜ 물폭탄…경북엔 시간당 72㎜ 쏟아져",
      "밤사이 경기북부 150㎜ 폭우…홍수·산사태 주의보"
    ],
    "국제": [
      "사상 최대 유행 경고 에볼라, 대응 약물 개발까지 최소 6개월",
      "‘나홀로 집에2’ 비둘기 아줌마 브렌다 프리커 별세…향년 81세",
      "美, 이스라엘 파견 공중급유기 전쟁 초 수준으로 늘린다",
      "‘자율주행 원조’ 日의 굴욕…로보택시 한 대도 없는 나라 됐다"
    ],
    "IT": [
      "사상 최대 유행 경고 에볼라, 대응 약물 개발까지 최소 6개월",
      "“쉰 목소리, 입속 궤양, 목의 혹… 3주 지나면 두경부암 의심하라”[베스트...",
      "허사비스 “최첨단 AI 검증할 국제기구 필요”",
      "공급과잉-투자지연 우려에 반도체株 휘청… 美빅테크 실적 촉각"
    ]
  }
}