{
  "updated_at": "2026-07-16T19:48:58.995298+09:00",
  "updated_at_display": "2026-07-16 19:48:58 KST",
  "script_version": "v9.0 - 2026-07-14 (자동 토큰갱신저장 + 실패알림)",
  "weather": {
    "location": "서울",
    "current": {
      "icon": "⛅",
      "label": "구름 조금",
      "temp": 25.7,
      "humidity": 74,
      "wind": 3.6
    },
    "daily": [
      {
        "date": "07/16",
        "weekday": "목",
        "icon": "☁️",
        "label": "흐림",
        "max": 29.0,
        "min": 22.0,
        "rain": 34
      },
      {
        "date": "07/17",
        "weekday": "금",
        "icon": "🌦️",
        "label": "강한 이슬비",
        "max": 28.0,
        "min": 22.0,
        "rain": 51
      },
      {
        "date": "07/18",
        "weekday": "토",
        "icon": "🌧️",
        "label": "강한 비",
        "max": 26.0,
        "min": 24.0,
        "rain": 91
      },
      {
        "date": "07/19",
        "weekday": "일",
        "icon": "🌦️",
        "label": "이슬비",
        "max": 28.0,
        "min": 24.0,
        "rain": 93
      }
    ]
  },
  "weather_seoul": {
    "location": "서울",
    "current": {
      "icon": "⛅",
      "label": "구름 조금",
      "temp": 25.7,
      "humidity": 74,
      "wind": 3.6
    },
    "daily": [
      {
        "date": "07/16",
        "weekday": "목",
        "icon": "☁️",
        "label": "흐림",
        "max": 29.0,
        "min": 22.0,
        "rain": 34
      },
      {
        "date": "07/17",
        "weekday": "금",
        "icon": "🌦️",
        "label": "강한 이슬비",
        "max": 28.0,
        "min": 22.0,
        "rain": 51
      },
      {
        "date": "07/18",
        "weekday": "토",
        "icon": "🌧️",
        "label": "강한 비",
        "max": 26.0,
        "min": 24.0,
        "rain": 91
      },
      {
        "date": "07/19",
        "weekday": "일",
        "icon": "🌦️",
        "label": "이슬비",
        "max": 28.0,
        "min": 24.0,
        "rain": 93
      }
    ]
  },
  "weather_bundang": {
    "location": "분당",
    "current": {
      "icon": "⛅",
      "label": "구름 조금",
      "temp": 24.3,
      "humidity": 90,
      "wind": 4.2
    },
    "daily": [
      {
        "date": "07/16",
        "weekday": "목",
        "icon": "☁️",
        "label": "흐림",
        "max": 28.0,
        "min": 21.0,
        "rain": 49
      },
      {
        "date": "07/17",
        "weekday": "금",
        "icon": "🌧️",
        "label": "약한 비",
        "max": 27.0,
        "min": 21.0,
        "rain": 52
      },
      {
        "date": "07/18",
        "weekday": "토",
        "icon": "🌧️",
        "label": "강한 비",
        "max": 27.0,
        "min": 24.0,
        "rain": 92
      },
      {
        "date": "07/19",
        "weekday": "일",
        "icon": "🌧️",
        "label": "약한 비",
        "max": 28.0,
        "min": 23.0,
        "rain": 95
      }
    ]
  },
  "indices": [
    {
      "name": "코스피",
      "value": "6,820.60",
      "change": "▼6.37%"
    },
    {
      "name": "코스닥",
      "value": "791.84",
      "change": "▼4.53%"
    }
  ],
  "global_indices": [
    {
      "name": "다우존스",
      "value": "52,658.64",
      "change": "▲0.29%"
    },
    {
      "name": "나스닥",
      "value": "26,269.23",
      "change": "▲0.62%"
    },
    {
      "name": "S&P 500",
      "value": "7,572.40",
      "change": "▲0.38%"
    }
  ],
  "movers": {
    "up": [
      {
        "code": "044380",
        "name": "주연테크",
        "change": "▲30.00%"
      },
      {
        "code": "011090",
        "name": "에넥스",
        "change": "▲29.95%"
      },
      {
        "code": "002070",
        "name": "비비안",
        "change": "▲29.94%"
      }
    ],
    "down": [
      {
        "code": "006490",
        "name": "프리티",
        "change": "▲24.06%"
      },
      {
        "code": "520101",
        "name": "미래에셋 레버리지 SK하이닉스 단일종목ETN",
        "change": "▲23.16%"
      },
      {
        "code": "760013",
        "name": "키움 레버리지 반도체TOP10 ETN",
        "change": "▲20.65%"
      }
    ],
    "volume": [
      {
        "code": "252670",
        "name": "KODEX 200선물인버스2X",
        "change": "▲13.64%"
      },
      {
        "code": "114800",
        "name": "KODEX 인버스",
        "change": "▲6.85%"
      },
      {
        "code": "252710",
        "name": "TIGER 200선물인버스2X",
        "change": "▲15.05%"
      }
    ]
  },
  "headlines": {
    "정치": [
      "진통 속 원구성 합의 ‘경기도의회’…상임위원장, 민주당 12·국힘 1 선출",
      "李, 또 유튜브 ‘댓글 투표’…“16세이하 SNS 차단 찬성하면 1번”",
      "김태효 前안보실 1차장 구속 유지…법원, 적부심 청구 기각",
      "‘여중생 성매매’ 청주시의원 휴대폰 포렌식…‘성착취물’ 흔적 찾는다"
    ],
    "경제": [
      "메리츠, 홈플러스 긴급자금 2000억 승인…회생절차 재개",
      "“종부세, 주택수 아닌 가액으로 개편해 ‘똘똘한 한 채’ 쏠림 막아야”",
      "李, 또 유튜브 ‘댓글 투표’…“16세이하 SNS 차단 찬성하면 1번”",
      "2000억원 수혈, 급한 불 끈 홈플러스…정상화는 ‘산 넘어 산’"
    ],
    "사회": [
      "경찰, 잠실 개표소 진입 막은 30대女 구속영장",
      "기상청 온도보다 3도 더 덥다…올여름 서울서 가장 뜨거운 ‘이 동네’",
      "공수처, ‘서해 피격 위증 의혹’ 인천해경 등 압수수색",
      "진통 속 원구성 합의 ‘경기도의회’…상임위원장, 민주당 12·국힘 1 선출"
    ],
    "국제": [
      "우크라 드론, 국경서 1400km 떨어진 러 대형 정유공장 타격",
      "주성치 ‘쿵푸여자축구’, 한국팀 비하 논란…“반칙·외모 집착 묘사”",
      "“AI 남친·여친 그만 사귀라”…中정부가 ‘챗봇 연애’ 막는 속사정",
      "TSMC, 2분기 영업익 65% 껑충…“美공장에 148조원 투자”"
    ],
    "IT": [
      "李, 또 유튜브 ‘댓글 투표’…“16세이하 SNS 차단 찬성하면 1번”",
      "제헌절 남부 최대 80㎜…토요일 중부엔 200㎜ 폭우 쏟아진다",
      "“AI 남친·여친 그만 사귀라”…中정부가 ‘챗봇 연애’ 막는 속사정",
      "[시승기] 장거리에서 진가 드러낸 프리미엄 대형 SUV…‘GMC 아카디아’"
    ]
  }
}