{
  "updated_at": "2026-06-25T13:00:59.912985+09:00",
  "updated_at_display": "2026-06-25 13:00:59 KST",
  "weather": {
    "current": {
      "icon": "☁️",
      "label": "흐림",
      "temp": 24.0,
      "humidity": 63,
      "wind": 3.1
    },
    "daily": [
      {
        "date": "06/25",
        "weekday": "목",
        "icon": "🌧️",
        "label": "약한 비",
        "max": 24.0,
        "min": 19.0,
        "rain": 75
      },
      {
        "date": "06/26",
        "weekday": "금",
        "icon": "🌤️",
        "label": "대체로 맑음",
        "max": 28.0,
        "min": 17.0,
        "rain": 31
      },
      {
        "date": "06/27",
        "weekday": "토",
        "icon": "⛅",
        "label": "구름 조금",
        "max": 31.0,
        "min": 19.0,
        "rain": 4
      },
      {
        "date": "06/28",
        "weekday": "일",
        "icon": "☁️",
        "label": "흐림",
        "max": 31.0,
        "min": 20.0,
        "rain": 10
      }
    ]
  },
  "weather_seoul": {
    "current": {
      "icon": "☁️",
      "label": "흐림",
      "temp": 24.0,
      "humidity": 63,
      "wind": 3.1
    },
    "daily": [
      {
        "date": "06/25",
        "weekday": "목",
        "icon": "🌧️",
        "label": "약한 비",
        "max": 24.0,
        "min": 19.0,
        "rain": 75
      },
      {
        "date": "06/26",
        "weekday": "금",
        "icon": "🌤️",
        "label": "대체로 맑음",
        "max": 28.0,
        "min": 17.0,
        "rain": 31
      },
      {
        "date": "06/27",
        "weekday": "토",
        "icon": "⛅",
        "label": "구름 조금",
        "max": 31.0,
        "min": 19.0,
        "rain": 4
      },
      {
        "date": "06/28",
        "weekday": "일",
        "icon": "☁️",
        "label": "흐림",
        "max": 31.0,
        "min": 20.0,
        "rain": 10
      }
    ]
  },
  "weather_bundang": {
    "current": {
      "icon": "☁️",
      "label": "흐림",
      "temp": 21.1,
      "humidity": 81,
      "wind": 4.3
    },
    "daily": [
      {
        "date": "06/25",
        "weekday": "목",
        "icon": "🌦️",
        "label": "강한 이슬비",
        "max": 22.0,
        "min": 18.0,
        "rain": 67
      },
      {
        "date": "06/26",
        "weekday": "금",
        "icon": "🌦️",
        "label": "약한 이슬비",
        "max": 27.0,
        "min": 17.0,
        "rain": 25
      },
      {
        "date": "06/27",
        "weekday": "토",
        "icon": "☁️",
        "label": "흐림",
        "max": 30.0,
        "min": 16.0,
        "rain": 0
      },
      {
        "date": "06/28",
        "weekday": "일",
        "icon": "☁️",
        "label": "흐림",
        "max": 29.0,
        "min": 18.0,
        "rain": 10
      }
    ]
  },
  "indices": [
    {
      "name": "코스피",
      "value": "8,929.64",
      "change": "▲5.41%"
    },
    {
      "name": "코스닥",
      "value": "895.39",
      "change": "▼1.53%"
    }
  ],
  "us_indices": [
    {
      "name": "다우존스",
      "value": "51,848.90",
      "change": "▲0.35%"
    },
    {
      "name": "S&P500",
      "value": "7,358.22",
      "change": "▼0.10%"
    },
    {
      "name": "나스닥",
      "value": "25,476.64",
      "change": "▼0.43%"
    }
  ],
  "movers": {
    "up": [
      {
        "name": "한투 인버스은선물 ETN",
        "change": "▲29.98%"
      },
      {
        "name": "SK이터닉스",
        "change": "▲29.93%"
      },
      {
        "name": "금호전기",
        "change": "▲26.40%"
      }
    ],
    "down": [
      {
        "name": "보해양조",
        "change": "▲30.00%"
      },
      {
        "name": "비비안",
        "change": "▲29.92%"
      },
      {
        "name": "SHD",
        "change": "▲27.44%"
      }
    ],
    "volume": [
      {
        "name": "KODEX 200선물인버스2X",
        "change": "▲12.68%"
      },
      {
        "name": "KODEX 인버스",
        "change": "▲6.14%"
      },
      {
        "name": "삼성 인버스 2X WTI원유 선물 ETN",
        "change": "▲12.50%"
      }
    ]
  },
  "headlines": {
    "정치": [
      "李대통령, 부산 어선 침몰 사고에 “가용 자원 총동원해 인명 구조”",
      "한성숙 “아버지 말씀은 좀…” 野 “父 얘기 먼저 꺼내”",
      "국힘 개혁파 “장동혁 재선거 주장은 해당행위…사퇴해야”",
      "한성숙, ‘주적 어디냐’ 질문에 “韓 위협하는 곳은 다 적…北은 위협이자 동포”"
    ],
    "경제": [
      "빌딩 숲에서 찾는 내면의 숨…룰루레몬, 서소문서 심신 치유축제 개최",
      "[속보]‘몬테레이 참사’ 홍명보호, 조 3위 추락…자력 32강 진출 실패",
      "“13년 만의 신작” GTA6 예약 판매 시작…PC 버전은 제외",
      "‘9000피’ 회복 눈앞…마이크론 역대급 실적에 ‘삼전닉스’ 급등"
    ],
    "사회": [
      "휴양림 산책 중 발 헛디뎠다…3m 아래로 추락한 70대 숨져",
      "대법 “‘김남국 코인 중독 범죄자’ 장예찬 발언, 악의적 단정 어려워”…파기환송",
      "광명 아파트 공사장서 작업자 철근에 깔려…2명 중경상",
      "‘이스타항공 채용비리’ 창업주 이상직·前임원들, 대법서 무죄 확정"
    ],
    "국제": [
      "‘몬테레이 참사’ 홍명보호, 조 3위 추락…자력 32강 진출 실패",
      "[속보]‘몬테레이 참사’ 홍명보호, 조 3위 추락…자력 32강 진출 실패",
      "100kg 찍고 건강검진 ‘경고’…37세 아빠, 73kg까지 감량했다",
      "네타냐후 “작년 이란 공격 트럼프 허락 안받아…통보했을 뿐”"
    ],
    "IT": [
      "[주간보안동향] ‘모두의 창업’ 해킹 사고, 합격자 5000명 아이디어 털렸다 外",
      "“13년 만의 신작” GTA6 예약 판매 시작…PC 버전은 제외",
      "“가짜 계정 2만5000개 동원”…앤스로픽, 알리바바 ‘AI 무단 사용’ 주장",
      "‘삼전닉스 풍향계’ 마이크론 역대급 실적…“메모리 부족 지속”"
    ]
  }
}