{
  "updated_at": "2026-07-16T10:29:19.558857+09:00",
  "updated_at_display": "2026-07-16 10:29:19 KST",
  "script_version": "v9.0 - 2026-07-14 (자동 토큰갱신저장 + 실패알림)",
  "weather": {
    "location": "서울",
    "current": {
      "icon": "⛅",
      "label": "구름 조금",
      "temp": 25.6,
      "humidity": 84,
      "wind": 1.4
    },
    "daily": [
      {
        "date": "07/16",
        "weekday": "목",
        "icon": "☁️",
        "label": "흐림",
        "max": 30.0,
        "min": 22.0,
        "rain": 28
      },
      {
        "date": "07/17",
        "weekday": "금",
        "icon": "🌧️",
        "label": "강한 비",
        "max": 28.0,
        "min": 22.0,
        "rain": 53
      },
      {
        "date": "07/18",
        "weekday": "토",
        "icon": "🌧️",
        "label": "강한 비",
        "max": 27.0,
        "min": 22.0,
        "rain": 91
      },
      {
        "date": "07/19",
        "weekday": "일",
        "icon": "🌧️",
        "label": "강한 소나기",
        "max": 28.0,
        "min": 23.0,
        "rain": 95
      }
    ]
  },
  "weather_seoul": {
    "location": "서울",
    "current": {
      "icon": "⛅",
      "label": "구름 조금",
      "temp": 25.6,
      "humidity": 84,
      "wind": 1.4
    },
    "daily": [
      {
        "date": "07/16",
        "weekday": "목",
        "icon": "☁️",
        "label": "흐림",
        "max": 30.0,
        "min": 22.0,
        "rain": 28
      },
      {
        "date": "07/17",
        "weekday": "금",
        "icon": "🌧️",
        "label": "강한 비",
        "max": 28.0,
        "min": 22.0,
        "rain": 53
      },
      {
        "date": "07/18",
        "weekday": "토",
        "icon": "🌧️",
        "label": "강한 비",
        "max": 27.0,
        "min": 22.0,
        "rain": 91
      },
      {
        "date": "07/19",
        "weekday": "일",
        "icon": "🌧️",
        "label": "강한 소나기",
        "max": 28.0,
        "min": 23.0,
        "rain": 95
      }
    ]
  },
  "weather_bundang": {
    "location": "분당",
    "current": {
      "icon": "⛅",
      "label": "구름 조금",
      "temp": 26.1,
      "humidity": 87,
      "wind": 3.8
    },
    "daily": [
      {
        "date": "07/16",
        "weekday": "목",
        "icon": "☁️",
        "label": "흐림",
        "max": 29.0,
        "min": 21.0,
        "rain": 35
      },
      {
        "date": "07/17",
        "weekday": "금",
        "icon": "🌧️",
        "label": "강한 비",
        "max": 27.0,
        "min": 21.0,
        "rain": 59
      },
      {
        "date": "07/18",
        "weekday": "토",
        "icon": "🌧️",
        "label": "강한 비",
        "max": 26.0,
        "min": 22.0,
        "rain": 93
      },
      {
        "date": "07/19",
        "weekday": "일",
        "icon": "🌧️",
        "label": "비",
        "max": 28.0,
        "min": 23.0,
        "rain": 96
      }
    ]
  },
  "indices": [
    {
      "name": "코스피",
      "value": "6,788.63",
      "change": "▼6.81%"
    },
    {
      "name": "코스닥",
      "value": "792.80",
      "change": "▼4.42%"
    }
  ],
  "global_indices": [
    {
      "name": "다우존스",
      "value": "52,658.64",
      "change": "▲0.29%"
    },
    {
      "name": "나스닥",
      "value": "26,269.23",
      "change": "▲0.62%"
    },
    {
      "name": "S&P 500",
      "value": "7,572.40",
      "change": "▲0.38%"
    }
  ],
  "movers": {
    "up": [
      {
        "code": "044380",
        "name": "주연테크",
        "change": "▲30.00%"
      },
      {
        "code": "011090",
        "name": "에넥스",
        "change": "▲29.95%"
      },
      {
        "code": "002070",
        "name": "비비안",
        "change": "▲29.94%"
      }
    ],
    "down": [
      {
        "code": "520101",
        "name": "미래에셋 레버리지 SK하이닉스 단일종목ETN",
        "change": "▲23.18%"
      },
      {
        "code": "006490",
        "name": "프리티",
        "change": "▲21.29%"
      },
      {
        "code": "760013",
        "name": "키움 레버리지 반도체TOP10 ETN",
        "change": "▲20.84%"
      }
    ],
    "volume": [
      {
        "code": "252670",
        "name": "KODEX 200선물인버스2X",
        "change": "▲14.77%"
      },
      {
        "code": "114800",
        "name": "KODEX 인버스",
        "change": "▲7.62%"
      },
      {
        "code": "360750",
        "name": "TIGER 미국S&P500",
        "change": "▲0.13%"
      }
    ]
  },
  "headlines": {
    "정치": [
      "[속보]대법, ‘통일교 1억 수수’ 권성동 징역 2년 확정",
      "정청래 “보완수사권 전면 폐지해야…다 함께 힘 모으자”",
      "정점식 “정부 입맛따라 적용되는 노란고무줄법…본인들만 빠져나가”",
      "김영진 “유시민 표현 과해…李 ‘수사·기소 분리’ 원칙 한번도 버린 적 없어”"
    ],
    "경제": [
      "김정관 “반도체 호황, 사회 전체 호황 아냐…흉년 대비해야”",
      "“버틸 비축유가 없다”…호르무즈 재봉쇄에 원유시장 ‘초긴장’",
      "수도권 30억 아파트 3년 새 6배…‘초고가 기준’ 어디로",
      "네이버, 풀필먼트 솔루션 ‘N배송 FBN’ 도입… N배송 새벽·일요배송 확대"
    ],
    "사회": [
      "[속보]‘통일교 1억’ 권성동 징역 2년 확정…의원직 상실",
      "[속보]대법 “포스코, 사내하청 직원 직접고용해야” 불법파견 인정",
      "탁구치다 쓰러진 70대, 비번 경찰이 살렸다…10분간 CPR",
      "병원 근무자가 아프면?…“38도 고열에 스스로 주사 꼽고 버텼다” 씁쓸"
    ],
    "국제": [
      "“버틸 비축유가 없다”…호르무즈 재봉쇄에 원유시장 ‘초긴장’",
      "이란 테헤란 전광판에 ‘관 속 트럼프’ 등장…“트럼프 죽일 것”",
      "금리의 역습, 도쿄 파워커플은 살아남을까(feat. 버블 붕괴론) [딥다이브]",
      "무력충돌 와중 구금 미국인 석방한 이란…트럼프 “선의에 감사”"
    ],
    "IT": [
      "라셀릭 세포재생의학연구소, KOITA ‘기업부설연구소’ 인정 획득",
      "“근육만 강해지는 게 아니었다”…운동이 심장 신경까지 바꾼다",
      "‘생활병’ 된 말라리아… 운동-캠핑하다 감염 많아",
      "[전문의 칼럼]비영리 ‘의료법인’이 지역필수의료 붕괴 막을 버팀목"
    ]
  }
}