{
  "updated_at": "2026-06-17T09:01:01.443408+09:00",
  "updated_at_display": "2026-06-17 09:01:01 KST",
  "weather": {
    "current": {
      "icon": "🌤️",
      "label": "대체로 맑음",
      "temp": 23.4,
      "humidity": 77,
      "wind": 3.7
    },
    "daily": [
      {
        "date": "06/17",
        "weekday": "수",
        "icon": "🌦️",
        "label": "이슬비",
        "max": 29.0,
        "min": 20.0,
        "rain": 47
      },
      {
        "date": "06/18",
        "weekday": "목",
        "icon": "🌦️",
        "label": "약한 이슬비",
        "max": 30.0,
        "min": 20.0,
        "rain": 56
      },
      {
        "date": "06/19",
        "weekday": "금",
        "icon": "☁️",
        "label": "흐림",
        "max": 32.0,
        "min": 21.0,
        "rain": 51
      },
      {
        "date": "06/20",
        "weekday": "토",
        "icon": "🌦️",
        "label": "약한 이슬비",
        "max": 29.0,
        "min": 23.0,
        "rain": 60
      }
    ]
  },
  "weather_seoul": {
    "current": {
      "icon": "🌤️",
      "label": "대체로 맑음",
      "temp": 23.4,
      "humidity": 77,
      "wind": 3.7
    },
    "daily": [
      {
        "date": "06/17",
        "weekday": "수",
        "icon": "🌦️",
        "label": "이슬비",
        "max": 29.0,
        "min": 20.0,
        "rain": 47
      },
      {
        "date": "06/18",
        "weekday": "목",
        "icon": "🌦️",
        "label": "약한 이슬비",
        "max": 30.0,
        "min": 20.0,
        "rain": 56
      },
      {
        "date": "06/19",
        "weekday": "금",
        "icon": "☁️",
        "label": "흐림",
        "max": 32.0,
        "min": 21.0,
        "rain": 51
      },
      {
        "date": "06/20",
        "weekday": "토",
        "icon": "🌦️",
        "label": "약한 이슬비",
        "max": 29.0,
        "min": 23.0,
        "rain": 60
      }
    ]
  },
  "weather_bundang": {
    "current": {
      "icon": "🌤️",
      "label": "대체로 맑음",
      "temp": 23.6,
      "humidity": 83,
      "wind": 8.2
    },
    "daily": [
      {
        "date": "06/17",
        "weekday": "수",
        "icon": "🌦️",
        "label": "약한 이슬비",
        "max": 28.0,
        "min": 19.0,
        "rain": 59
      },
      {
        "date": "06/18",
        "weekday": "목",
        "icon": "🌦️",
        "label": "약한 이슬비",
        "max": 29.0,
        "min": 20.0,
        "rain": 67
      },
      {
        "date": "06/19",
        "weekday": "금",
        "icon": "☁️",
        "label": "흐림",
        "max": 31.0,
        "min": 20.0,
        "rain": 51
      },
      {
        "date": "06/20",
        "weekday": "토",
        "icon": "🌦️",
        "label": "약한 이슬비",
        "max": 27.0,
        "min": 22.0,
        "rain": 70
      }
    ]
  },
  "indices": [
    {
      "name": "코스피",
      "value": "8,633.44",
      "change": "▼1.07%"
    },
    {
      "name": "코스닥",
      "value": "1,018.41",
      "change": "▼0.03%"
    }
  ],
  "us_indices": [
    {
      "name": "다우존스",
      "value": "51,999.67",
      "change": "▲0.64%"
    },
    {
      "name": "S&P500",
      "value": "7,511.35",
      "change": "▼0.57%"
    },
    {
      "name": "나스닥",
      "value": "26,376.34",
      "change": "▼1.15%"
    }
  ],
  "movers": {
    "up": [
      {
        "name": "제주은행",
        "change": "▲4.30%"
      },
      {
        "name": "한화갤러리아",
        "change": "▲2.53%"
      },
      {
        "name": "오리온홀딩스",
        "change": "▲0.92%"
      }
    ],
    "down": [
      {
        "name": "키움 레버리지 반도체TOP10 ETN",
        "change": "▲2.94%"
      },
      {
        "name": "강남제비스코",
        "change": "▲2.69%"
      },
      {
        "name": "KODEX MSCI Korea",
        "change": "▲1.89%"
      }
    ],
    "volume": [
      {
        "name": "KODEX 코스닥150선물인버스",
        "change": "▲0.70%"
      },
      {
        "name": "TIGER 배당커버드콜액티브",
        "change": "▲1.13%"
      },
      {
        "name": "KODEX 2차전지산업레버리지",
        "change": "▲1.53%"
      }
    ]
  },
  "headlines": {
    "정치": [
      "조국 “2028년 총선서 평택을 결과 전국화되지 않도록 성찰할 것”",
      "빅터 차 “시진핑 비핵화 침묵은 北 핵보유 지위 용인 시사”",
      "G7회의에 모인 정상들",
      "여야 “45일간 투표용지 국조” 합의… 위원장 국힘"
    ],
    "경제": [
      "그릭요거트 요즘, 산리오캐릭터즈와 함께 ‘요즘 썸머 랜드’ 프로모션 실시",
      "우리은행, 40억 규모 금융사고…“할인분양 사기 수사 진행”",
      "“8·11·14단지 수주 정조준”… 대우건설, 목동서 조합원 접점 넓힌다",
      "“MOU에 이란 석유 판매 허용 포함…유조선 이미 봉쇄선 통과”"
    ],
    "사회": [
      "우리은행, 40억 규모 금융사고…“할인분양 사기 수사 진행”",
      "아산서 좌회전 승용차와 오토바이 충돌…10대 숨져",
      "잘 가다 갑자기 폭주 쏘나타, 70대 여성 사망…‘급발진’ 여부 등 수사",
      "낮 최고 32도 무더위…전국 곳곳 소나기"
    ],
    "국제": [
      "우크라로 눈 돌린 G7, 러 압박…트럼프 “원유 제재 재개 가능”",
      "민주콩고 에볼라확진 837명으로 증가..내전· 주민 반발로 방역 난관",
      "이란, 월드컵서 ‘권총 세리머니’ 해명…“평범한 세리머니였다”",
      "“美, 이스라엘의 ‘종전 MOU’ 열람 요구 거절”"
    ],
    "IT": [
      "“매일 걷는데도 건강검진 빨간불?”…310만명 분석해 보니 [바디플랜]",
      "아이스커피 한 모금에 찌릿한다면…여름철 ‘민감성 치아’ 주의보",
      "AI의 恨 인간이 켜다",
      "“美, 첨단AI 수출통제 뒤엔… 中연계 의심 韓통신사” 논란"
    ]
  }
}